Metadata-Version: 1.0
Name: sbbbxl-distrib
Version: 0.1
Summary: Gaussian and Binomial distributions
Home-page: UNKNOWN
Author: Saiphan Bruner
Author-email: UNKNOWN
License: UNKNOWN
Platform: UNKNOWN
